LICENSE
README.md
pyproject.toml
setup.cfg
setup.py
src/sereia/__init__.py
src/sereia/mapper.py
src/sereia/sereia.py
src/sereia.egg-info/PKG-INFO
src/sereia.egg-info/SOURCES.txt
src/sereia.egg-info/dependency_links.txt
src/sereia.egg-info/requires.txt
src/sereia.egg-info/top_level.txt
src/sereia/candidate_network/__init__.py
src/sereia/candidate_network/candidate_network.py
src/sereia/candidate_network/candidate_network_handler.py
src/sereia/database/__init__.py
src/sereia/database/mongo_handler.py
src/sereia/database/mongo_iter.py
src/sereia/evaluation/__init__.py
src/sereia/evaluation/evaluation_handler.py
src/sereia/evaluation/evaluation_report.py
src/sereia/index/__init__.py
src/sereia/index/babel_hash.py
src/sereia/index/index_build.py
src/sereia/index/index_handler.py
src/sereia/index/schema_graph.py
src/sereia/index/schema_index.py
src/sereia/index/value_index.py
src/sereia/keyword_match/__init__.py
src/sereia/keyword_match/keyword_match.py
src/sereia/keyword_match/keyword_match_handler.py
src/sereia/query_match/__init__.py
src/sereia/query_match/query_match.py
src/sereia/query_match/query_match_handler.py
src/sereia/utils/__init__.py
src/sereia/utils/config_handler.py
src/sereia/utils/document_traverser.py
src/sereia/utils/generate_evaluation_report.py
src/sereia/utils/graph.py
src/sereia/utils/keyword_query.py
src/sereia/utils/logger.py
src/sereia/utils/memory.py
src/sereia/utils/mongo_query_builder.py
src/sereia/utils/ordinal.py
src/sereia/utils/plots.py
src/sereia/utils/printmd.py
src/sereia/utils/result.py
src/sereia/utils/shift_tab.py
src/sereia/utils/similarity.py
src/sereia/utils/tf_iaf.py
src/sereia/utils/timestr.py
src/sereia/utils/tokenizer.py
src/sereia/utils/truncate.py
src/sereia/utils/utils.py